[
    {
        "name":"介绍",
        "id":2111231602,
        "issues":[
            {
                "id":2111231603,
                "title":"SwiftUI 是什么？",
                "number":71
            }
        ]
    },
    {
        "name":"视图组件使用",
        "id":2112021514,
        "issues":[
            {
                "id":2112021924,
                "title":"SwiftUI 对标的 UIKit 视图",
                "number":100
            },
            {
                "id":2112021517,
                "title":"Text",
                "number":92
            },
            {
                "id":2202171557,
                "title":"Link",
                "number":147
            },
            {
                "id":2202171945,
                "title":"Label",
                "number":148
            },
            {
               "id":2202181842,
               "title":"TextEditor",
               "number":149
            },
            {
                "id":2202211627,
                "title":"TextField",
                "number":150
            },
            {
                "id":2202162023,
                "title":"Button",
                "number":145
            },
            {
                "id":2202221445,
                "title":"Stack",
                "number":151
            }
        ]
    }
]
